{
  "run": {
    "iso": "2026-07-14T22:26:40.760Z",
    "stamp": "2026-07-14T22-26-40-760Z",
    "local": "15 Jul 2026, 03:56:40"
  },
  "timeZone": "Asia/Kolkata",
  "url": "https://sameer-local-azure.sameersaurabh.xyz/",
  "okStatusRange": {
    "min": 200,
    "max": 399
  },
  "expectedTexts": [
    "MediaAnalytics",
    "Live Feed"
  ],
  "markerResults": {
    "MediaAnalytics": true,
    "Live Feed": false
  },
  "errors": [
    "Missing expected frontend marker(s): Live Feed."
  ],
  "ok": false,
  "responseMs": 821,
  "status": 200,
  "statusText": "OK",
  "finalUrl": "https://sameer-local-azure.sameersaurabh.xyz/",
  "contentType": "text/html; charset=utf-8",
  "bodyBytes": 8865,
  "statusOk": true,
  "markersOk": false
}