{
  "run": {
    "iso": "2026-06-13T23:52:04.680Z",
    "stamp": "2026-06-13T23-52-04-680Z",
    "local": "14 Jun 2026, 05:22:04"
  },
  "timeZone": "Asia/Kolkata",
  "url": "https://sameer-local-azure.sameersaurabh.xyz/",
  "okStatusRange": {
    "min": 200,
    "max": 399
  },
  "expectedTexts": [
    "MediaAnalytics",
    "Live Feed"
  ],
  "markerResults": {
    "MediaAnalytics": true,
    "Live Feed": true
  },
  "errors": [],
  "ok": true,
  "responseMs": 785,
  "status": 200,
  "statusText": "OK",
  "finalUrl": "https://sameer-local-azure.sameersaurabh.xyz/",
  "contentType": "text/html; charset=utf-8",
  "bodyBytes": 9988,
  "statusOk": true,
  "markersOk": true
}