{
  "run": {
    "iso": "2026-07-17T17:08:02.734Z",
    "stamp": "2026-07-17T17-08-02-734Z",
    "local": "17 Jul 2026, 22:38:02"
  },
  "timeZone": "Asia/Kolkata",
  "url": "https://sameer-local-azure.sameersaurabh.xyz/",
  "okStatusRange": {
    "min": 200,
    "max": 399
  },
  "expectedTexts": [
    "MediaAnalytics",
    "Live Feed"
  ],
  "markerResults": {},
  "errors": [
    "Request failed: timeout after 15000ms"
  ],
  "ok": false,
  "responseMs": 15004,
  "status": null,
  "contentType": "",
  "bodyBytes": 0,
  "statusOk": false,
  "markersOk": false
}